sample_MetaData/__init__.py
sample_MetaData/main.py
gen_cv_manager-0.0.2.dist-info/LICENSE
gen_cv_manager-0.0.2.dist-info/METADATA
gen_cv_manager-0.0.2.dist-info/WHEEL
gen_cv_manager-0.0.2.dist-info/require.txt
gen_cv_manager-0.0.2.dist-info/top_level.txt
gen_cv_manager-0.0.2.dist-info/RECORD
